explay/__init__.py
explay/agg_func.py
explay/openpyxl_ext.py
explay/post_func.py
explay/source.py
explay/utils.py
explay_testt-0.2.0.data/scripts/exp
explay_testt-0.2.0.dist-info/DESCRIPTION.rst
explay_testt-0.2.0.dist-info/METADATA
explay_testt-0.2.0.dist-info/RECORD
explay_testt-0.2.0.dist-info/WHEEL
explay_testt-0.2.0.dist-info/metadata.json
explay_testt-0.2.0.dist-info/top_level.txt
